galaxy_jukebox/__init__.py
galaxy_jukebox/__main__.py
galaxy_jukebox/builder.py
galaxy_jukebox/main.py
galaxy_jukebox/split_lines.py
galaxy_jukebox/unsplit_lines.py
galaxy_jukebox/vector.py
galaxy_jukebox-1.0.0.dist-info/entry_points.txt
galaxy_jukebox-1.0.0.dist-info/LICENSE
galaxy_jukebox-1.0.0.dist-info/WHEEL
galaxy_jukebox-1.0.0.dist-info/METADATA
galaxy_jukebox-1.0.0.dist-info/RECORD
