Metadata-Version: 2.1
Name: galaxy-jukebox
Version: 1.0.0
Summary: Schematic exporter for Minecraft Note Block Studio, making a galaxy-shaped redstone jukebox, that plays the song.
Keywords: minecraft,note,block,noteblock,schematic,redstone
Author-email: 1234ab <nevenincs007@gmail.com>
Classifier: License :: OSI Approved :: MIT License
Classifier: Programming Language :: Python :: 3
Requires-Dist: pynbs >=1.1.0
Requires-Dist: mcschematic >=11.4
Project-URL: Home, https://github.com/4321ba/Galaxy_Jukebox
